{
    "Contacto": {
        "Nombre": null,
        "Correo": [
            "betzcal89@gmail.com"
        ],
        "Celular": [
            "56961448426"
        ],
        "Linkedin": null
    },
    "Nombre archivo": "1567721974989-CV_Betzaida_Calanche",
    "Licencias-Certificaciones": [],
    "Palabras Claves": [
        "Puntual",
        "Gestión",
        "Aprender",
        "Responsabilidad"
    ],
    "Educacion": {
        "Universidades:": [],
        "Grado_mas_alto": [
            "Ingeniera"
        ]
    },
    "Lenguajes": [
        "Inglés"
    ],
    "Experiencia": "experiencia profesional\njulio 2019/actualidad cámara y producción.\nrugby chile.\n\ncamarógrafo de partido de primera división del rugby\nmasculino.\n\ntransmisiones vía streaming.\noctubre 2018/actualidad coordinador de\nservicios/cgs.\nbitelco diebold chile ltda.\n\ncoordinación de servicios para atms de diferentes\nbancos.\n\nseguimiento de ruta.\n\nmanejo con personal técnico y mesa de gestión de\nbancos.\nabril 2018/octubre 2018 técnico junior.\nbitelco diebold chile ltda.\n\ninstalación de sistemas anti-skimmig para atm proyecto\nbanco santander.\nseptiembre 2017/enero 2018 ingeniero de móvil\npara transmisiones de televisión.\nvisión digital producciones c.a.\n\nmanejo de personal de aproximadamente 30 personas.\n\noperador de video.\n\nmanejo de equipos blackmagic.\n\nsupervisión de transmisión.\n\nbeisbol, basket, futbol, conciertos.\nenero 2016/agosto 2017 supervisor y coordinador\nde obras y proyectos.\nbglw proyectos eléctricos c.a.\n\nmanejo de personal de aproximadamente 10 personas.\n\nejecución y supervisión de proyectos en instalaciones\neléctricas en el edifico procter gamble.\nmarzo/diciembre 2015 asistente de dirección de\nobras.\nelectrificaciones reca c.a.\n\nmanejo de personal\n\nsupervisión\nde\nproyectos\nde\ncanalizaciones\ne\ninstalaciones eléctricas en el edifico procter gamble.\nagosto 2014/diciembre 2015 pasante de dirección\nde tecnología e informática.\nalcaldía de libertador de caracas.\n\nlevantamiento de información.\n\ndiseño de red de transporte y red de acceso para las\nsedes.\n\nsimulación de radio enlaces.\nhabilidades profesionales\nmicrosoft office\ncisco packet tracer\nautocad 2d\nvisio\nradio mobile\nmaprex\nseguridad y riesgo\neléctrico\ncableado eléctrico\nblackmagic\n",
    "Resumen": "regular bueno excelente\nbueno muy bueno excelente\nbetzaida e. calanche r.\ningeniera electricista\nmención comunicaciones\n10 de enero de 1989. venezolana\noperador de video y técnico de unidad móvil en\ntransmisiones deportivas, manejo de equipos blackmagic,\ndispuesta a aprender, apotar conocimiento, disponibilidad\ninmediata, responsable, puntual, organizada, soltera.\n",
    "Referencias": "",
    "Skills": [
        "Visio",
        "Autocad",
        "Office"
    ]
}