{
    "Nombre": "Andrea Cruz Marciales ",
    "Correo": [
        "a.cruzmarciales@gmail.com"
    ],
    "Linkedin": null,
    "Celular": "+18062392571",
    "Skills": [
        "Office"
    ],
    "Licencias-Certificaciones": [
        "TOEFL"
    ],
    "Grado": [
        "Maestría"
    ],
    "Palabras Claves": [
        "Liderazgo",
        "Gestión",
        "Negociación",
        "Estrategia",
        "Responsabilidad",
        "Adaptable",
        "Puntual"
    ],
    "Educacion": [],
    "Lenguajes": [
        "Inglés avanzado",
        "Español nativo",
        "Inglés",
        "Español"
    ],
    "Experiencia": "experiencia laboral\nnossa galvis abogados\ndepartamento derecho inmobiliario y corporativo.\ntipo de contrato laboral término indefinido.\nperiodo 11 de febrero actualidad\nfunciones acompañamiento legal a los clientes de la firma en temas relacionados con el giro\nordinario de sus negocios, en especial asesoría legal en constitución de sociedades, escisión de\nsociedades, capitalización de sociedades y liquidación de sociedades. por otro lado asesoría en\ntrámites de licencias de construcción ante las entidades distritales o municipales\ncorrespondientes, trámites para la obtención de planes parciales ante las distintas entidades\ndistritales o municipales, estructuración de fideicomisos inmobiliarios, estructuración\nherramientas jurídicas de vinculación de clientes a proyectos inmobiliarios. negociación con\nclientes interesados en adquirir locales comerciales y/u hoteles. elaboración de promesas de\ncompraventa, escrituración de los bienes inmuebles y asesoría en temas de cumplimiento del\nestatuto del consumidor.\ncnk consultores s.a.s.\ndepartamento jurídico. cargo directora jurídica.\ntipo de contrato laboral término indefinido.\nperiodo 17 de septiembre de 2018 8 de febrero de 2019.\nfunciones llevar a cabo la estructuración legal de los negocios inmobiliarios y fiduciarios de la\ncompañía incluyendo estudio de títulos. llevar a cabo la negociación con los propietarios de los\ninmuebles que la compañía pretende adquirir para el desarrollo de proyectos inmobiliarios.\nrealizar la estructuración de las minutas de contratos y requerimientos de las garantías\ncontractuales, aplicadas a cada caso. identificar y valorar los riesgos de los nuevos negocios de\nla compañía. plantear y llevar a cabo alternativas legales para trámites jurídicos ante entidades\nde control y registro de escrituras públicas. buscar métodos y programas de cobro de cartera, pre\njurídico y judicial de proveedores y clientes. llevar a cabo la estructuración y el procedimiento\npara la respuesta legal a requerimientos, quejas, peticiones del cliente interno y externo de la\ncompañía. conocer los procesos judiciales y conciliatorios de la compañía, estructurar y coordinar\na los abogas externos que los lleven según la necesidad del proceso. llevar a cabo la\nestructuración legal de las asesorías y consultorías que la compañía realiza incluye apoyo en la\noferta comercial, elaboración de los convenios, acuerdo y contratos y posteriormente la\nliquidación del negocio. asesorar al departamento comercial en las estrategias de ventas,\ncumpliendo con las normas aplicables a la materia y revisar desde el punto legal los distintos\nmedios y herramientas comerciales para la debida comercialización de los proyectos.\npinilla gonzalez prieto abogados.\ndepartamento derecho urbanístico. cargo abogado.\ntipo de contrato laboral término indefinido.\nperiodo 13 de marzo de 2017 12 enero 2018.\nfunciones elaboración de estudios de títulos, formulación y modificación de planes parciales,\nsolicitud y trámite de licencias urbanísticas, asesoramiento en la modificación, revisión y ajuste\nde planes de ordenamiento territorial, planes básicos de ordenamiento territorial y esquemas de\nordenamiento territorial, elaboración de conceptos normativos y otros temas propios del área,\nelaboración de escritos jurídicos dirigidos a diferentes entidades, investigaciones normativas sobre\ntemas del área, atención y asistencia jurídica a requerimientos de los clientes del área, envío de\ndocumentación e información a los clientes del área, saneamiento de bienes, trámites ante las\nempresas prestadoras de servicios públicos domiciliarios, solicitud y trámite de actualización de\ncabida y linderos, y control y seguimiento de trámites administrativos.\nprabyc ingenieros s.a.s.\ngerencia jurídica. cargo abogado.\ntipo de contrato laboral término indefinido.\nperiodo 4 de abril de 2016 5 de enero de 2017.\nfunciones acompañamiento legal al departamento comercial de la compañía en todo lo\nrelacionado a las estrategias de ventas y promoción utilizado para la adecuada comercialización\nde los proyectos. revisión con el área comercial de los problemas del área para darle una solución\npertinente minimizada así futuros riesgos. elaboración de respuestas a derechos de petición y\ntutelas. apoyo en la elaboración de reglamentos de propiedad horizontal para copropiedades\ndestinadas a vivienda, apoyo jurídico a los diversos departamentos de la compañía, apoyo jurídico\nen temas relacionados con el estatuto del consumidor, contestación y seguimiento a procesos\nante la superintendencia de industria y comercio, apoyo en trámite ante entidades estatales,\nresolución de problemas jurídicos, atención a los usuarios externos.\nsuperficies colombia s.a.s.\ncargo abogado dirección jurídica.\ntipo de contrato laboral término indefinido.\nperiodo 17 de febrero de 2014-30 de marzo de 2016.\nfunciones única abogada de superficies colombia s.a.s., realizar la estructuración de los\nnegocios inmobiliarios incluido el apoyo jurídico en la consecución de los inmuebles, la\nelaboración de los estudios de títulos, elaboración de los documentos jurídicos para la adquisición\nde los inmuebles, estructuración de los negocios fiduciarios. elaboración y revisión de las minutas\nde promesas de compraventa y/o contratos de vinculación de beneficiarios de área y las escrituras\nde transferencia de dominio. elaboración de los reglamentos de propiedad horizontal.\nacompañamiento legal en los trámites de licencia de urbanismo, construcción y/o intervención\ndel espacio público. asesoría legal para el correcto trámite ante las entidades prestadoras de\nservicios públicos domiciliarios. acompañamiento legal ante las diversas entidades públicas para\nel correcto desarrollo de los proyectos. elaboración de respuestas pertinentes a los clientes\ninternos y externos de la compañía y la elaboración de los distintos procesos jurídicos de la\ncompañía para los proceso de certificación y auditorias. elaboración de contratos de obra y\nliquidación de los mismos.\npedro gómez y cía. s.a.\ndepartamento jurídico. cargo abogado junior.\ntipo de contrato laboral término indefinido.\nperiodo 22 de octubre de 2012 -14 de febrero de 2014.\nfunciones elaboración de contratos de promesa de compraventa para inmuebles destinados a\nvivienda y comercio, elaboración de contratos de arrendamiento para inmuebles destinados a\nvivienda y comercio, elaboración de reglamentos de propiedad horizontal para copropiedades\ndestinadas a vivienda y comercio, elaboración de manuales de vitrinismo, contestación de\nderechos de petición, apoyo jurídico a los diversos departamentos de la compañía, gestión en\ntrámite de cancelaciones de hipoteca de mayor extensión, gestión en trámites de desenglobes y\nenglobes de predios, gestión en trámites de desenglobe catastral, estudio de títulos, resolución\nde problemas jurídicos, atención a los usuarios externos.\nospinas y cía. s.a.\ndepartamento jurídico. cargo analista jurídica.\ntipo de contrato laboral término indefinido.\nperiodo 11 de octubre de 2.010 - 15 de octubre 2.012.\nfunciones elaboración de contratos, elaboración y contestación de derechos de petición, apoyo\njurídico a los diversos departamentos de la compañía, gestión en trámite de cancelaciones de\nhipoteca de mayor extensión, resolución de problemas jurídicos, atención a los usuarios externos,\napoyo en la elaboración de minutas de compraventa y manejo de clientes externos.\n\nidiomas, habilidades tecnológicas e intereses personales\n\nespañol nativo\n\ninglés avanzado, toefl\n\nmanejo superior de las herramientas de google drive y microsoft office.\n\nintereses personales pilates, trx, yoga y cocina.\n\n",
    "Resumen": "perfil profesional\nabogada de la universidad de los andes con estudios complementarios en antropología. tengo\nexperiencia en temas inmobiliarios, urbanísticos y de estructuración de negocios. tengo altas\nhabilidades en investigación y resolución de problemas jurídicos. excelentes relaciones\ninterpersonales, liderazgo, adaptabilidad al cambio y apertura al aprendizaje continuo, puntual,\norganizada, responsable y con gran capacidad para asumir retos. tengo una orientación clara a\nla obtención de logros y resultados.\n\n",
    "Referencias": "referencias personales\njuan manuel gonzalez.\nabogado socio fundador.\npinilla gonzález y prieto abogados.\ncelular 3143336421\ngerman acosta fuentes.\nabogado - director jurídico.\nospinas y cía. s.a.\nteléfono 1 3267060. extensión 145.\nvictor ibarra palacios.\nabogado director jurídico.\narias serna y saravia s.a.\nteléfono 1 2570266. extensión 502.\njose sebastian caceres.\nabogado - subgerente jurídico.\nprabyc ingenieros s.a.s.\ncelular 3165256698.\njosé hernan arias.\nabogado director jurídico.\namarilo s.a.\nteléfono 6340000.\n",
    "Nombre archivo": "1567552274976-HOJA_DE_VIDA_ANDREA_CRUZ_2019"
}