{
    "Nombre": "Francisco Javier Fredes ",
    "Correo": [
        "f.fredes.s@gmail.com"
    ],
    "Linkedin": null,
    "Celular": [
        "56982991867"
    ],
    "Skills": [
        "Erp",
        "Office",
        "Solomon",
        "Sap"
    ],
    "Grado": [
        "Magíster"
    ],
    "Palabras Claves": [
        "Analizar",
        "Gestión",
        "Adaptable",
        "Análisis",
        "Colaboración",
        "Disposición"
    ],
    "Educacion": [
        "Universidad Andrés Bello"
    ],
    "Lenguajes": [],
    "Nombre archivo": "1567626688126-Francisco_Javier_Fredes_Silva_C.V."
}