{
    "Contacto": {
        "Nombre": null,
        "Correo": [
            "ro.garin087@gmail.com"
        ],
        "Celular": "0981215726",
        "Linkedin": null
    },
    "Nombre archivo": "1568050391127-CV_Roberto_Garin_Silva",
    "Licencias-Certificaciones": [
        "CLASE B",
        "LICENCIA DE CONDUCIR"
    ],
    "Palabras Claves": [
        "Compromiso",
        "Análisis",
        "Gestión",
        "Proactividad",
        "Responsabilidad"
    ],
    "Educacion": {
        "Universidades:": [
            "Universidad Técnica Federico Santa María",
            "Instituto Profesional DUOC UC",
            "Universidad Andrés Bello"
        ],
        "Grado_mas_alto": [
            "Ingeniería"
        ]
    },
    "Lenguajes": [
        "Inglés"
    ],
    "Experiencia": "experiencia profesional marzo 2005 junio 2005 oficina de contabilidad. oficina de contabilidad eduardo vásquez. autocad. nivel medio autocad civil. nivel medio cargo asistente técnico contable. función ayudante de contabilidad en la elaboración de libros contables iva y renta, generación y emisión de formularios iva y renta. diciembre 2011 - marzo 2012 constructora gardilcic. elaboración obras civiles codelco división andina. cargo asistente oficina técnica. función realización practica laboral en codelco división andina instalaciones constructora gardilcic, generación de cartas gantt y programas de control, elaboración de precios unitarios y cubicaciones, inspección por parte del departamento de obras civiles en la ejecución de los proyectos, elaboración de carpetas de control de puntos de carguío. marzo 2012- junio 2012 constructora jsb. cargo supervisor obras constructivas. función planificación y gestión de obras, coordinación de logística, estudio de costos, contratación de personal, cubicación, cotización y compra de materiales. asesoría constructiva a departamentos de estudio. ",
    "Resumen": null,
    "Referencias": "referencias cargo inspector obras eléctricas. función inspección y revisión cámaras tipo para servicios eléctricos, elaboración de procedimientos de seguridad para el resguardo de accidentes de trabajo, elaboración de precios unitarios y cubicaciones. german silva bustamante ingeniero eléctrico cel 09 81215726. mayo 2013 - junio 2013 empresa constructora fann. jaime silva bustamante gerente general constructora jsb cel09- 58958060. gonzalo santibáñez gerente general syg cel 0962064802 cargo oficina técnica profesional de terreno función asistente técnico en obra reparaciones varias mall espacio urbano viña del mar, control personal de trabajo en el cumplimiento de horario, elaboración de catastro de partidas criticas a realizar obra reparaciones varias mall espacio urbano, creación cartas gantt y análisis de ruta crítica del proyecto. junio 2013 - octubre 2013 empresa constructora syg. cargo oficina técnica. función elaboración de precios unitarios y cubicaciones, estudio de proyectos constructivos, elaboración de estados de pagos, creación de cartas gantt y rutas críticas. noviembre 2014 - junio 2018 empresa constructora jsb. cargo oficina técnica. función encargado oficina técnica , realización estudio de propuestas y licitaciones a través de plataforma mercado publico, emisión de precios unitarios y cubicaciones, estudio de proyectos de remodelaciones y obras civiles para la universidad técnica federico santa maría, elaboración de precios unitarios , gestión de mejora de procesos constructivos, elaboración de procedimientos de seguridad para el resguardo de trabajadores , elaboración de estados de pago para cada obra realizada, emisión de documentos facturas electrónicas, generación de planos autocad, generación cartas gantt project, elaboración contratos de trabajos , emisión y revisión documentos aclaratorios de deuda documento f-30, generación de cotización y compra de material para obras constructivas, elaboración de planillas excel para control de personal, elaboración planillas excel para control de materiales, elaboración planillas excel para control estados de pagos, supervisión avance de obras. . roberto simón garín silva. teléfono / móvil 09-81879079 e-mail ro.garin087@gmail.com domicilio alvarez 528 departamento 53 b viña del mar. ",
    "Skills": [
        "Autocad",
        "Office",
        "Excel",
        "Microsoft project"
    ]
}