{
    "Contacto": {
        "Nombre": "Loreto Yesenia Ibañez ",
        "Correo": [
            "Loreto.ibanez.m@gmail.com"
        ],
        "Celular": "+56994880059",
        "Linkedin": null
    },
    "Nombre archivo": "1568402610338-LORETO_YESENIA_IBAÑEZ_MUÑOZ-19_3",
    "Licencias-Certificaciones": [
        "CLASE B",
        "LICENCIA DE CONDUCIR"
    ],
    "Palabras Claves": [
        "Responsabilidad",
        "Análisis",
        "Resiliencia",
        "Puntual",
        "Motivación",
        "Gestión",
        "Liderar"
    ],
    "Educacion": {
        "Universidades:": [
            "Universidad De La Serena",
            "Universidad de Aconcagua",
            "Universidad Pedro de Valdivia"
        ],
        "Grado_mas_alto": [
            "Magíster"
        ]
    },
    "Lenguajes": [
        "Inglés"
    ],
    "Experiencia": "experiencia laboral 569 94880059 / 512754360. loreto.ibanez.m@gmail.com ingeniería civil de minas y licenciada en ciencias de la ingeniería. universidad pedro de valdivia, la serena. 2010 2016 ingeniero civil de minas de la universidad pedro de valdivia, profesional con la capacidad de aplicar conocimientos científicos para entender los problemas en la minería e identificar, procesar y entregar soluciones competentes. gran capacidad de incorporación y dirección de equipos de trabajo y de investigación e inclusión de nuevas tecnologías. capaz de proponer programas para cumplir con las políticas nacionales e internacionales en el tema ambiental, compatibilizar actuaciones empresariales con objetivos ambientales además de diseñar y aplicar acciones tendientes a una mayor eficacia industrial, ambiental y energética poseer la capacidad de ser el nexo entre la industria, los agentes sociales y gubernamentales involucrados, tener la capacidad de programar, organizar y aplicar monitoreos ambientales y supervisiones ambientales en terreno, y crear las bases para desarrollar un magíster en el área ambiental.  mar 2017 a mar 2018, docente técnico profesional, explotación minera, colegio pablo neruda, coquimbo. docente de especialidad, 44 horas, de cursos de enseñanza media 1 a 4 medio, donde realice programas de estudios relacionados con la minería, tales como muestreo minero en explotaciones mineras, lectura e interpretaciones de planos mineros, taller de software, taller de metrología.  may 2016 a feb 2107, organizadora del evento deportivo de fútbol playa femenino, coquimbo. formé parte de la comisión organizadora del evento deportivo de fútbol femenino a nivel nacional, de la región de coquimbo. gestioné los recursos, permisos, patrocinios, etc. planifique los requisitos, la estadía y alimentación de los participantes, los reglamentos de competencias de juego, y obviamente una evaluación exhaustiva de costos.  ene a mar 2014, activation laboratories ltda. actlabs, coquimbo. practicante, con una ejecución más de 560 horas en el laboratorio de análisis de muestras de minerales, provenientes de distintas mineras de la región de coquimbo, además de la recepción de información del equipo utilizado, y de los distintos procesos en general. 2018 universidad de la serena diplomado en gestión ambiental y sustentabilidad energética otras ",
    "Resumen": "resumen ",
    "Referencias": "",
    "Skills": []
}