{
    "Nombre": "Miguel Ángel Escalonilla ",
    "Correo": [
        "comercial.escalonilla@gmail.com"
    ],
    "Linkedin": null,
    "Celular": "+56984516765",
    "Skills": [
        "Ventas",
        "Wordpress",
        "Marketing",
        "Office",
        "Excel",
        "Power point",
        "Word"
    ],
    "Grado": [
        "Ingeniería"
    ],
    "Palabras Claves": [
        "Adaptable",
        "Responsabilidad",
        "Análisis",
        "Motivación",
        "Negociación",
        "Apasionado",
        "Proactividad"
    ],
    "Educacion": [
        "Universidad del Desarrollo"
    ],
    "Lenguajes": [
        "Inglés avanzado",
        "Inglés"
    ],
    "Nombre archivo": "1568299344768-Miguel_Ángel_Escalonilla_Palma_CV"
}