{
    "Contacto": {
        "Nombre": "María Jesús Morandé ",
        "Correo": [
            "mjmorandeb@gmail.com"
        ],
        "Celular": "+56998244881",
        "Linkedin": null
    },
    "Nombre archivo": "1568242971074-CV_MJesusMorande",
    "Licencias-Certificaciones": [],
    "Palabras Claves": [
        "Responsabilidad",
        "Análisis",
        "Adaptable"
    ],
    "Educacion": {
        "Universidades:": [],
        "Grado_mas_alto": [
            "Ingeniería"
        ]
    },
    "Lenguajes": [
        "Inglés",
        "Inglés avanzado"
    ],
    "Experiencia": "experiencia laboral dic 2017 a la fecha proyecto de emprendimiento de almuerzos para oficinas. dic 2013 nov 2017 asistente comercial en administracion de activos bice inversiones encargada de llevar la relación diaria con clientes de altos patrimonios, preparar periódicamente informes de rentabilidades, inversión de la cartera de clientes en money market, renta fija y renta variable local, entre otros. jun 2012 dic 2012 analista de finanzas en atton hoteles encargada de las proyecciones semanales de la caja de la empresa, tomar depósitos, compra- venta de dólares, evaluación de proyectos. además, periódicamente preparaba reportes y presentaciones para el comité de desarrollo y directorio. may 2012jun 2012 asistente en dirección de operaciones en universidad de los andes dic 2011 ene 2012 práctica profesional en bice inversiones equipo de estudios renta variable de agf 2008 2012 ayudante en diversos ramos en universidad de los andes ",
    "Resumen": "maría jesús morandé bascuñán dirección particular warren smith 47, dpto. 49, las condes, santiago, chile. celular 56 9 9824 4881 e-mail mjmorandeb@gmail.com ingeniero comercial de la universidad de los andes. con 5 años de experiencia en empresas de los rubros hotelero y financiero. principalmente me he desempeñado en funciones en áreas de administración, finanzas y comercial. el último año y medio he estado desarrollando un proyecto de emprendimiento. competencias desarrolladas en administración, análisis y planificación. soy organizada, responsable, movida, con facilidad de adaptación a equipos de trabajo y al cambio. ",
    "Referencias": "",
    "Skills": [
        "Excel",
        "Power point",
        "Word"
    ]
}