{
    "Nombre": "L Mar ",
    "Correo": "carolina.castillo@outlook.com",
    "Linkedin": null,
    "Celular": "+56956679116",
    "Skills": [
        "Base de datos"
    ],
    "Licencias-Certificaciones": [],
    "Grado": [
        "Ingeniería"
    ],
    "Palabras Claves": [
        "Liderar",
        "Responsabilidad",
        "Análisis",
        "Gestión",
        "Colaboración"
    ],
    "Educacion": [
        "Instituto Profesional DUOC UC",
        "Pontificia Universidad Catolica de Chile",
        "Universidad de Santiago de Chile",
        "Universidad Católica de Chile"
    ],
    "Lenguajes": [
        "Inglés"
    ],
    "Nombre archivo": "1569892763906-CV_Carolina_Castillo_H"
}