{
    "Contacto": {
        "Nombre": "Licenciado Objeti ",
        "Correo": "m.paz.rodriguezc@gmail.com",
        "Celular": "+56990158868",
        "Linkedin": null
    },
    "Nombre archivo": "1570409925214-MariaPazRodrigueza_actualCV1",
    "Licencias-Certificaciones": [
        "CLASE B",
        "LICENCIA DE CONDUCIR"
    ],
    "Palabras Claves": [
        "Creativo",
        "Disposición",
        "Modelamiento",
        "Analizar",
        "Comprometido",
        "Ética",
        "Liderazgo",
        "Proactividad",
        "Responsabilidad"
    ],
    "Educacion": {
        "Universidades:": [],
        "Grado_mas_alto": [
            "Ingeniería"
        ]
    },
    "Lenguajes": [
        "Inglés intermedio",
        "Inglés"
    ],
    "Experiencia": "experiencia laboral bice vida. junio de 2019 a la fecha. agente comercial de seguros individuales y mantención de clientes. asesorar de la mejor manera a los clientes entregando protección, seguridad y ahorro, analizando los posibles escenarios con la finalidad de cubrir sus expectativas y necesidades. productoras basic one y viba. marzo de 2014 a la fecha. producción y realización de eventos poseo conocimientos para organizar y producir eventos de alta calidad. para ello he desarrollado ",
    "Resumen": null,
    "Referencias": "",
    "Skills": [
        "Word",
        "Visio",
        "Office",
        "Power point",
        "Excel",
        "Access"
    ]
}