{
    "Contacto": {
        "Nombre": "Lectura Dsi Cortina ",
        "Correo": [],
        "Celular": "",
        "Linkedin": null
    },
    "Nombre archivo": "1571007085422-Informe_de_Lectura.docx",
    "Licencias-Certificaciones": [],
    "Palabras Claves": [
        "Modelamiento",
        "Responsabilidad",
        "Motivación",
        "Análisis",
        "Adaptable",
        "Ética",
        "Disciplina"
    ],
    "Educacion": {
        "Universidades:": [],
        "Grado_mas_alto": []
    },
    "Lenguajes": [],
    "Experiencia": " Informe De Lectura Dsi Cortina, Adela 2017. Aporofobia, el rechazo al pobre. Buenos Aires. Paidós. Docente Erick Oñate J. 1 Señala la historia del término aporofobia y cómo la autora establece una relación entre xenofobia y aporofobia capitulo 1. La manera en que las naciones afrontan el tema de la migración responde a discursos que los mismos partidos políticos utilizan en sus discursos, aquellos que ocupan al extranjero como chivo expiatorio para conseguir adeptos, instauran este odio el cual se replica por la sociedad. Pero en otros casos se manifiesta al comprender que el problema no es el extranjero, ya que un europeo turista que llega en horda en época estival no presenta un problema, es más un extranjero con capital inversor es bien venido al país. El problema es indudablemente que vemos al extranjero perseguido políticamente o en busca de mejor calidad de vida, como un enemigo que reducirá mis propias opciones, me quitara mis oportunidades e incluso podría quedarse con mi trabajo. 2 Señala cuatro argumentos centrales que permitan dar cuenta del origen o causa de los delitos de odio al pobre capítulo 2 y de los discursos de odio capítulo 3. También se producen cuando hay un comportamiento de desprecio y maltrato en un discurso de odio que promueve e incita el odio a través de justificaciones basadas en deudas que se consideran históricas pero de las cuales no existe el menor argumento, ya que simplemente se le atañe carga o responsabilidad a alguien que pertenece al grupo al cual se le acusa. En cuyos casos son grupos a los cuales constantemente se les persigue por ser diferentes y es la propagación del odio. Pero que hay que esclarecer, a la hora de atacar se le ataca al individuo no la grupo o colectivo, por lo cual queda manifestada la intolerancia. Existen casos donde el odio surge del maltrato de estas minorías y la constante vejación deriva en un dolor que se traduce en un discurso de odio o una enconada animadversión. Todo esto replica los modelos de odio que si bien acá es contra una sociedad que ha validado y permitido constantemente estos atropellos y esto significativamente, aumenta el odio o el rechazo contra aquel que oprimió, pero que siempre se manifiesta y materializa en una persona, un enemigo al que reconocer y contra el cual orientar el odio. 3 Señala dos argumentos de la autora para indicar que nuestro cerebro es aporóforo capítulo 4 y de cómo la hospitalidad cosmopolita es posibilidad de cambio capítulo 8. Vivimos en un mundo en contradicción al sueño que Martín Luther King pregonó, estamos ajenos a la conciencia moral en niveles alarmantes donde la justicia no solo es ciega sino que además posee una balanza cargada y averiada. De lo anterior podemos rescatar que según la ontogénesis existen 3 niveles de cómo opera la moral de los humanos, partiendo por aquello que me beneficia a mi es lo que considero justo, en segundo lugar aquello que beneficia a mi grupo o a mis cercanos, pero finalmente en el último lugar aquello que va en pro de la humanidad y que debiese ser el máximo nivel de la moral social. Este análisis propende a que racionalizamos las acciones y dependiendo de cuanta justicia tienen, la catalogamos como buena o mala para la humanidad y por ende seria lo correcto. Tenemos la idea de las dos dimensiones de la conciencia humana en el cual hay una que se refiere a la conciencia y otra a la reputación, según Nietzsche es más fácil acallar la conciencia y vivir con la reputación, esto porque la reputación es un costo que el hombre está dispuesto a pagar si la recompensa a los actos han valido dentro de los parámetros del sujeto. El ejemplo esta en la historia del anillo de Giges el cual narra lo que hace un hombre con un anillo que vuelve a un hombre invisible con solo darle dos vueltas. Y producto de lo anterior conquista un reino seduce a la reina y mata al gobernante, impulsado por la motivación al premio a conquistar, la leyenda es cuestionada al punto de mencionar que un hombre correcto o moralmente social tendría el mismo destino o final de uno moralmente impropio ya que la diferencia solo es la voluntad y las ganas de conseguir el premio. Por lo consiguiente la moral social se avoca a lo más importante y antiguo de la filosofía desde Grecia hasta nuestros tiempos. 5 Construye un glosario de 15 términos, con su respectivo significado, que ayuden a comprender la teoría de la aporofobia. 1. Xenofobia Rechazo a los extranjeros. 7. Discriminación Trato diferente y perjudicial que se da a una persona por motivos de raza, sexo, ideas políticas, religión, etc. 9. Tradición Transmisión o comunicación de noticias, literatura popular, doctrinas, ritos, costumbres, etc., que se mantiene de generación en generación. 10. Equidad Cualidad que consiste en dar a cada uno lo que se merece en función de sus méritos o condiciones. 13. Moral Disciplina filosófica que estudia el comportamiento humano en cuanto al bien y el mal. 14. Progreso Mejora o avance que experimenta una persona o una cosa hacia un estado mejor, más avanzado o más desarrollado. 15. Intolerancia Actitud de la persona que no respeta las opiniones, ideas o actitudes de los demás si no coinciden con las propias ",
    "Resumen": "informe de lectura dsi cortina, adela 2017. aporofobia, el rechazo al pobre. buenos aires. paidós. nombre camila vasquez cornejo sección 2 docente erick oñate j. 1 señala la historia del término aporofobia y cómo la autora establece una relación entre xenofobia y aporofobia capitulo 1. históricamente la llegada de extranjeros a las sociedades ha impactado en el trato y en el modo de ver el sentimiento de pertenencia se entiende que las percepciones sociales son las que manifiestan el modo en que se construye el sentir y que da forma a los tratos que se dan para co el extranjero, dividiéndose en el trato a aquellos que están en tránsito y aquellos que llegan sin opción de retorno y deben emprender una colonización en el más primario de los sentidos de la palabra, para poder enfrentar no solo su historia que vienen trayendo, sino además las problemáticas acaecidas de los propios conflictos y prejuicios que la aporofobia trae para los extranjeros en el caso de la xenofobia, del latín xenos extranjero y phobos miedo podemos rastrear un origen muy antiguo a esta sensación de temor frente al encuentro e interrelación con lo desconocido. los atenienses, previo a su época de oro enfrentaron esta situación producto del apogeo de la polis griega, se vio enfrentada a la llegada de extranjeros que veían la posibilidad de surgir y tener una mejor vida. producto de lo anterior se les denominó metecos los cuales no tenían derechos e incluso no podían presentar casos legales ante las autoridades. pero esta situación cambio ante la llegada del ejército invasor persa que no discriminó entre atenienses ni metecos, y por consiguiente todos juntos lucharon en la defensa de la que consideraban su nación. la manera en que las naciones afrontan el tema de la migración responde a discursos que los mismos partidos políticos utilizan en sus discursos, aquellos que ocupan al extranjero como chivo expiatorio para conseguir adeptos, instauran este odio el cual se replica por la sociedad. pero en otros casos se manifiesta al comprender que el problema no es el extranjero, ya que un europeo turista que llega en horda en época estival no presenta un problema, es más un extranjero con capital inversor es bien venido al país. el problema es indudablemente que vemos al extranjero perseguido políticamente o en busca de mejor calidad de vida, como un enemigo que reducirá mis propias opciones, me quitara mis oportunidades e incluso podría quedarse con mi trabajo. 2 señala cuatro argumentos centrales que permitan dar cuenta del origen o causa de los delitos de odio al pobre capítulo 2 y de los discursos de odio capítulo 3. primero podemos argumentar que lo que propicia el odio es que se difumina la línea entre si este parte del que desprecia o es el despreciado, validaos las conductas cada vez que hacemos caso omiso o no defendemos y/o criticamos las conductas que propenden al odio, que normalizan las situaciones de discriminación, porque no nos afecta directamente. al hacer esto desacreditamos la labor de instituciones que buscan igualar y evitar estos comportamientos, como las causas feministas o de orientación sexual diferente. también se producen cuando hay un comportamiento de desprecio y maltrato en un discurso de odio que promueve e incita el odio a través de justificaciones basadas en deudas que se consideran históricas pero de las cuales no existe el menor argumento, ya que simplemente se le atañe carga o responsabilidad a alguien que pertenece al grupo al cual se le acusa. en cuyos casos son grupos a los cuales constantemente se les persigue por ser diferentes y es la propagación del odio. pero que hay que esclarecer, a la hora de atacar se le ataca al individuo no la grupo o colectivo, por lo cual queda manifestada la intolerancia. existen casos donde el odio surge del maltrato de estas minorías y la constante vejación deriva en un dolor que se traduce en un discurso de odio o una enconada animadversión. todo esto replica los modelos de odio que si bien acá es contra una sociedad que ha validado y permitido constantemente estos atropellos y esto significativamente, aumenta el odio o el rechazo contra aquel que oprimió, pero que siempre se manifiesta y materializa en una persona, un enemigo al que reconocer y contra el cual orientar el odio. indudablemente también es cuando se tiene en consideración la tradición por sobre la moral de la sociedad, cuando se ataca a los pobres o extranjeros solo para defender posiciones de poder que lucran o viven con la opresión del pobre y se validan constantemente en la ignorancia y el temor, caso ejemplar de brasil o ee.uu donde los grupos no son homogéneos pero tienen una larga tradición de controlar a través del odio y la ignorancia. tales como el kkk o el nuevo mondo. 3 señala dos argumentos de la autora para indicar que nuestro cerebro es aporóforo capítulo 4 y de cómo la hospitalidad cosmopolita es posibilidad de cambio capítulo 8. vivimos en un mundo en contradicción al sueño que martín luther king pregonó, estamos ajenos a la conciencia moral en niveles alarmantes donde la justicia no solo es ciega sino que además posee una balanza cargada y averiada. de lo anterior podemos rescatar que según la ontogénesis existen 3 niveles de cómo opera la moral de los humanos, partiendo por aquello que me beneficia a mi es lo que considero justo, en segundo lugar aquello que beneficia a mi grupo o a mis cercanos, pero finalmente en el último lugar aquello que va en pro de la humanidad y que debiese ser el máximo nivel de la moral social. este análisis propende a que racionalizamos las acciones y dependiendo de cuanta justicia tienen, la catalogamos como buena o mala para la humanidad y por ende seria lo correcto. ahora si bien es cierto, las instituciones políticas, económicas y sociales se basan en la herencia ilustrada, donde la razón y el bien social debiesen ser la máxima vs un modelo absolutista el cual no entregaba justicia social. apunta su moral en aquello que propende al bien común y por ende las instituciones educativas apuntan a este tipo de educación. pero por qué en este caso la sociedad quiere un mundo mejor pero elige uno peor, es porque somos débiles moralmente. la respuesta debería tener relación con la vertiginosidad con la que se vive. y adjunto a la debilidad moral propia del hombre según los autores ilustrados como hobbs o rousseau. también estos cambios son procesos de largo aliento que requieran ajustes y que probablemente la sociedad cree no vera, por ende prefiere escoger la satisfacción inmediata aun a sabiendas que no es lo correcto. por otra parte se cree que el cerebro es egoísta debido a nuestra biología y siglos de adaptación y competencia. los cuales han quedado en nuestro adn y por ende nos incitan a buscar el máximo beneficio en detrimento del prójimo. es en este caso más complicado que la moral actué correctamente cuando nos dejamos gobernar por tendencias evolutivas básicas que han impulsado la supervivencia y que ajustadas a la satisfacción del ganar o el beneficio inmediato propenderá a que hagamos una cosa muy distinta de los que pregonamos. 4 indica las ideas más relevantes, ejemplifica con hechos de realidad chilena y con un principio permanente de la dsi uno de los siguientes capítulos 5. conciencia y reputación 6. biomejora social 7. erradicar la pobreza, reducir la desigualdad. tenemos la idea de las dos dimensiones de la conciencia humana en el cual hay una que se refiere a la conciencia y otra a la reputación, según nietzsche es más fácil acallar la conciencia y vivir con la reputación, esto porque la reputación es un costo que el hombre está dispuesto a pagar si la recompensa a los actos han valido dentro de los parámetros del sujeto. el ejemplo esta en la historia del anillo de giges el cual narra lo que hace un hombre con un anillo que vuelve a un hombre invisible con solo darle dos vueltas. y producto de lo anterior conquista un reino seduce a la reina y mata al gobernante, impulsado por la motivación al premio a conquistar, la leyenda es cuestionada al punto de mencionar que un hombre correcto o moralmente social tendría el mismo destino o final de uno moralmente impropio ya que la diferencia solo es la voluntad y las ganas de conseguir el premio. por lo consiguiente la moral social se avoca a lo más importante y antiguo de la filosofía desde grecia hasta nuestros tiempos. el paso de los años ha devenido en que esta problemática se ha contrapuesto a las leyes naturales y el pacto social donde el hombre al vivir en sociedad, ha necesitado aparte de la delegación de su libertad y de las leyes para vivir en sociedad, unificar criterios lo cual es menester también del concepto más antiguo de moral. o moris o relativo a las costumbres que seria el espíritu primero de la conciencia social, ya que hablaría de lo que socialmente es correcto o costumbre y queda legitimado para la sociedad, pasando por sobre la motivación personal y elevando el sentido a la justicia social. desde tiempo de sócrates además se aduce que lo más importante ha sido la búsqueda de valores universales o denominado el bien común, pero está la diferencia más relevante entre le hombre y el animal, la voluntad de la ayuda recíproca, del preocuparse del prójimo, el consuelo, la justicia, la aversión a la inequidad y que ha sido reforzado por la vida en comunidad a lo largo de los siglos por instintos sociales y condiciones. a diferencia de la moralidad selectiva que tambalea ante la necesidad el hombre ha sido capaz de mostrar justicia cuando es en pro de la humanidad y la mera cuestión de debatirlo hace presenta la necesidad e inconformidad al respecto, puesto que es acucioso lograr avances y es menester de la humanidad lograr que un mundo socialmente justo y guiado por los más férreos sentimientos morales nos lleve más allá de donde hemos llegado. 5 construye un glosario de 15 términos, con su respectivo significado, que ayuden a comprender la teoría de la aporofobia. 1. xenofobia rechazo a los extranjeros. 2. autóctonos que ha nacido en el mismo lugar en que reside. 3. ontogénesis procesos que sufren los seres vivos desde la fecundación hasta su plenitud y madurez. 4. atonía falta de voluntad o energía para hacer cosas o para reaccionar física o moralmente ante algo. 5. humanidad conjunto de todos los seres humanos. 6. social que repercute beneficiosamente en toda la sociedad o en algún grupo social. 7. discriminación trato diferente y perjudicial que se da a una persona por motivos de raza, sexo, ideas políticas, religión, etc. 8. refugiados que se ha refugiado en un país extranjero a causa de una guerra o de sus ideas políticas o religiosas. 9. tradición transmisión o comunicación de noticias, literatura popular, doctrinas, ritos, costumbres, etc., que se mantiene de generación en generación. 10. equidad cualidad que consiste en dar a cada uno lo que se merece en función de sus méritos o condiciones. 11. deontología parte de la ética que trata de los deberes y principios que afectan a una profesión. 12. política ciencia que trata del gobierno y la organización de las sociedades humanas, especialmente de los estados. 13. moral disciplina filosófica que estudia el comportamiento humano en cuanto al bien y el mal. 14. progreso mejora o avance que experimenta una persona o una cosa hacia un estado mejor, más avanzado o más desarrollado. ",
    "Skills": [],
    "Referencias": ""
}