{
    "Nombre": "Gabriel García Lorca ",
    "Correo": [
        "gabogarcia@gmail.com"
    ],
    "Linkedin": null,
    "Celular": "20012005",
    "Skills": [
        "Marketing",
        "Ventas",
        "Word",
        "E-commerce"
    ],
    "Grado": [
        "Ingeniería"
    ],
    "Palabras Claves": [
        "Liderar",
        "Responsabilidad",
        "Estrategia",
        "Gestión",
        "Análisis"
    ],
    "Educacion": [
        "Inacap",
        "Universidad de Chile"
    ],
    "Lenguajes": [],
    "Nombre archivo": "1580320654107-CV_Gabriel_Garcia_Lorca"
}