{
    "Nombre": "Jesús Alonso Vásquez ",
    "Correo": [
        "jvasquezcole@hotmail.com"
    ],
    "Linkedin": null,
    "Celular": "967629267",
    "Skills": [
        "Word",
        "Ventas",
        "Excel",
        "Base de datos"
    ],
    "Grado": [
        "Administración de empresas"
    ],
    "Palabras Claves": [
        "Negociación",
        "Adaptable",
        "Análisis",
        "Liderazgo",
        "Gestión"
    ],
    "Educacion": [],
    "Lenguajes": [
        "Inglés"
    ],
    "Nombre archivo": "1580231848251-Curriculum_Vitae_-_Jesús_Alonso_Vásquez_Cole"
}