{
    "Nombre": "Diego Arturo Díaz ",
    "Correo": [
        "diego94@live.cl"
    ],
    "Linkedin": null,
    "Celular": "+56955334022",
    "Skills": [
        "Marketing",
        "Excel"
    ],
    "Licencias-Certificaciones": [],
    "Grado": [
        "Magíster"
    ],
    "Palabras Claves": [
        "Liderar",
        "Perfeccionista",
        "Gestión",
        "Estrategia",
        "Negociación"
    ],
    "Educacion": [
        "Universidad Adolfo Ibáñez"
    ],
    "Lenguajes": [
        "Alemán"
    ],
    "Nombre archivo": "1592840847221-CV_Diego_Diaz_OK-3"
}