{"Nombre": "Carolina Andrea Sierpe ", "Correo": "casierpe@uc.cl", "Linkedin": null, "Celular": "981921779", "Skills": ["Sql", "Stata", "Python", "Excel", "Erp", "Office"], "Grado": ["Ingeniería"], "Palabras Claves": ["Creativo", "Adaptable", "Apasionado", "Estrategia", "Aprender", "Negociación", "Responsabilidad", "Proactividad"], "Educacion": ["Universidad Católica de Chile"], "Lenguajes": ["Inglés"], "Nombre archivo": "/home/erwin/Genoma/cv-parser/1584562197232-CV_Carolina_Sierpe_Ing._Comercial"}