{"Nombre": "Erika Sotomayor Ulloa ", "Correo": ["eesotomayor@uc.cl"], "Linkedin": null, "Celular": "56989999586", "Skills": ["Sql", "Stata", "Power bi", "Python", "Marketing", "Machine learning", "Excel"], "Grado": ["Ingeniería"], "Palabras Claves": ["Análisis", "Estrategia", "Aprender", "Modelamiento", "Gestión"], "Educacion": ["Universidad Santo Tomas", "Universidad Católica de Chile"], "Lenguajes": ["Inglés"], "Nombre archivo": "/home/erwin/Genoma/cv-parser/1588283816605-CV_Erika_Sotomayor_Ulloa"}